django_typomatic/__init__.py
django_typomatic/__init__.pyi
django_typomatic/mappings.py
django_typomatic/test__init__.py
django_typomatic/management/__init__.py
django_typomatic/management/apps.py
django_typomatic/management/models.py
django_typomatic/management/commands/__init__.py
django_typomatic/management/commands/generate_ts.py
django_typomatic/management/settings/__init__.py
django_typomatic-2.5.2.dist-info/LICENSE
django_typomatic-2.5.2.dist-info/METADATA
django_typomatic-2.5.2.dist-info/WHEEL
django_typomatic-2.5.2.dist-info/top_level.txt
django_typomatic-2.5.2.dist-info/RECORD
