Metadata-Version: 2.1
Name: django-typomatic
Version: 2.5.2
Summary: A simple solution for generating Typescript interfaces from your Django Rest Framework Serializers.
Home-page: https://github.com/adenh93/django-typomatic
Author: Aden Herold
Author-email: aden.herold1@gmail.com
Keywords: Django,Django Rest Framework,DRF,Typescript,Python
Platform: any
License-File: LICENSE
Requires-Dist: django
Requires-Dist: djangorestframework
